fbKernelGaussiano/__init__.py
fbKernelGaussiano/modulo.py
fbKernelGaussiano-0.1.0.dist-info/METADATA
fbKernelGaussiano-0.1.0.dist-info/WHEEL
fbKernelGaussiano-0.1.0.dist-info/top_level.txt
fbKernelGaussiano-0.1.0.dist-info/RECORD
