Metadata-Version: 2.1
Name: fbKernelGaussiano
Version: 0.1.0
Summary: libreria para suavizar gráfica con kernel Gaussiano
Home-page: UNKNOWN
Author: Fabian
Author-email: fyamith.tovar@udea.edu.co
License: MIT
Platform: UNKNOWN
Requires-Python: >=3.10.12
Requires-Dist: matplotlib (==3.8.1)
Requires-Dist: numpy (==1.26.1)
Requires-Dist: pandas (==2.1.2)
